{
    "author": "TAP", 
    "color": "darkblue", 
    "controls": [
        {
            "name": "Semitone Shift", 
            "symbol": "Semitone"
        }, 
        {
            "name": "Rate Shift [%]", 
            "symbol": "Rate"
        }, 
        {
            "name": "latency", 
            "symbol": "Latency"
        }, 
        {
            "name": "Wet Level", 
            "symbol": "Wetlevel"
        }, 
        {
            "name": "Dry Level", 
            "symbol": "Drylevel"
        }
    ], 
    "label": "Pitch Shifter"
}